{"frames": [

{
	"filename": "carl-0",
	"frame": {"x":21,"y":24,"w":96,"h":72},
	"rotated": false,
	"trimmed": false,
	"spriteSourceSize": {"x":0,"y":0,"w":96,"h":72},
	"sourceSize": {"w":96,"h":72}
},
{
	"filename": "carl-1",
	"frame": {"x":1563,"y":51,"w":96,"h":72},
	"rotated": false,
	"trimmed": false,
	"spriteSourceSize": {"x":0,"y":0,"w":96,"h":72},
	"sourceSize": {"w":96,"h":72}
},
{
	"filename": "carl-2",
	"frame": {"x":1661,"y":51,"w":96,"h":72},
	"rotated": false,
	"trimmed": false,
	"spriteSourceSize": {"x":0,"y":0,"w":96,"h":72},
	"sourceSize": {"w":96,"h":72}
},
{
	"filename": "carl-3",
	"frame": {"x":1759,"y":63,"w":96,"h":72},
	"rotated": false,
	"trimmed": false,
	"spriteSourceSize": {"x":0,"y":0,"w":96,"h":72},
	"sourceSize": {"w":96,"h":72}
},
{
	"filename": "carl-4",
	"frame": {"x":1857,"y":63,"w":96,"h":72},
	"rotated": false,
	"trimmed": false,
	"spriteSourceSize": {"x":0,"y":0,"w":96,"h":72},
	"sourceSize": {"w":96,"h":72}
},
{
	"filename": "carl-5",
	"frame": {"x":1445,"y":101,"w":96,"h":72},
	"rotated": false,
	"trimmed": false,
	"spriteSourceSize": {"x":0,"y":0,"w":96,"h":72},
	"sourceSize": {"w":96,"h":72}
},
{
	"filename": "carl-6",
	"frame": {"x":1563,"y":125,"w":96,"h":72},
	"rotated": false,
	"trimmed": false,
	"spriteSourceSize": {"x":0,"y":0,"w":96,"h":72},
	"sourceSize": {"w":96,"h":72}
},
{
	"filename": "carl-7",
	"frame": {"x":1661,"y":125,"w":96,"h":72},
	"rotated": false,
	"trimmed": false,
	"spriteSourceSize": {"x":0,"y":0,"w":96,"h":72},
	"sourceSize": {"w":96,"h":72}
},
{
	"filename": "cassette-0",
	"frame": {"x":1,"y":1,"w":24,"h":15},
	"rotated": false,
	"trimmed": false,
	"spriteSourceSize": {"x":0,"y":0,"w":24,"h":15},
	"sourceSize": {"w":24,"h":15}
},
{
	"filename": "cassette-1",
	"frame": {"x":27,"y":1,"w":24,"h":15},
	"rotated": false,
	"trimmed": false,
	"spriteSourceSize": {"x":0,"y":0,"w":24,"h":15},
	"sourceSize": {"w":24,"h":15}
},
{
	"filename": "cassette-2",
	"frame": {"x":53,"y":1,"w":24,"h":15},
	"rotated": false,
	"trimmed": false,
	"spriteSourceSize": {"x":0,"y":0,"w":24,"h":15},
	"sourceSize": {"w":24,"h":15}
},
{
	"filename": "cube-0",
	"frame": {"x":79,"y":1,"w":21,"h":21},
	"rotated": false,
	"trimmed": false,
	"spriteSourceSize": {"x":0,"y":0,"w":21,"h":21},
	"sourceSize": {"w":21,"h":21}
},
{
	"filename": "cube-1",
	"frame": {"x":102,"y":1,"w":21,"h":21},
	"rotated": false,
	"trimmed": false,
	"spriteSourceSize": {"x":0,"y":0,"w":21,"h":21},
	"sourceSize": {"w":21,"h":21}
},
{
	"filename": "cube-2",
	"frame": {"x":125,"y":1,"w":21,"h":21},
	"rotated": false,
	"trimmed": false,
	"spriteSourceSize": {"x":0,"y":0,"w":21,"h":21},
	"sourceSize": {"w":21,"h":21}
},
{
	"filename": "cube-3",
	"frame": {"x":148,"y":1,"w":21,"h":21},
	"rotated": false,
	"trimmed": false,
	"spriteSourceSize": {"x":0,"y":0,"w":21,"h":21},
	"sourceSize": {"w":21,"h":21}
},
{
	"filename": "eyeball-00",
	"frame": {"x":171,"y":1,"w":18,"h":24},
	"rotated": false,
	"trimmed": false,
	"spriteSourceSize": {"x":0,"y":0,"w":18,"h":24},
	"sourceSize": {"w":18,"h":24}
},
{
	"filename": "eyeball-01",
	"frame": {"x":191,"y":1,"w":18,"h":39},
	"rotated": false,
	"trimmed": false,
	"spriteSourceSize": {"x":0,"y":0,"w":18,"h":39},
	"sourceSize": {"w":18,"h":39}
},
{
	"filename": "eyeball-02",
	"frame": {"x":1825,"y":1,"w":18,"h":54},
	"rotated": false,
	"trimmed": false,
	"spriteSourceSize": {"x":0,"y":0,"w":18,"h":54},
	"sourceSize": {"w":18,"h":54}
},
{
	"filename": "eyeball-03",
	"frame": {"x":1,"y":18,"w":18,"h":69},
	"rotated": false,
	"trimmed": false,
	"spriteSourceSize": {"x":0,"y":0,"w":18,"h":69},
	"sourceSize": {"w":18,"h":69}
},
{
	"filename": "eyeball-04",
	"frame": {"x":1543,"y":101,"w":18,"h":84},
	"rotated": false,
	"trimmed": false,
	"spriteSourceSize": {"x":0,"y":0,"w":18,"h":84},
	"sourceSize": {"w":18,"h":84}
},
{
	"filename": "eyeball-05",
	"frame": {"x":1881,"y":137,"w":18,"h":99},
	"rotated": false,
	"trimmed": false,
	"spriteSourceSize": {"x":0,"y":0,"w":18,"h":99},
	"sourceSize": {"w":18,"h":99}
},
{
	"filename": "eyeball-06",
	"frame": {"x":1665,"y":199,"w":18,"h":114},
	"rotated": false,
	"trimmed": false,
	"spriteSourceSize": {"x":0,"y":0,"w":18,"h":114},
	"sourceSize": {"w":18,"h":114}
},
{
	"filename": "eyeball-07",
	"frame": {"x":1685,"y":199,"w":18,"h":129},
	"rotated": false,
	"trimmed": false,
	"spriteSourceSize": {"x":0,"y":0,"w":18,"h":129},
	"sourceSize": {"w":18,"h":129}
},
{
	"filename": "eyeball-08",
	"frame": {"x":1949,"y":243,"w":18,"h":144},
	"rotated": false,
	"trimmed": false,
	"spriteSourceSize": {"x":0,"y":0,"w":18,"h":144},
	"sourceSize": {"w":18,"h":144}
},
{
	"filename": "eyeball-09",
	"frame": {"x":1969,"y":243,"w":18,"h":159},
	"rotated": false,
	"trimmed": false,
	"spriteSourceSize": {"x":0,"y":0,"w":18,"h":159},
	"sourceSize": {"w":18,"h":159}
},
{
	"filename": "eyeball-10",
	"frame": {"x":2009,"y":252,"w":18,"h":174},
	"rotated": false,
	"trimmed": false,
	"spriteSourceSize": {"x":0,"y":0,"w":18,"h":174},
	"sourceSize": {"w":18,"h":174}
},
{
	"filename": "eyeball-11",
	"frame": {"x":2029,"y":252,"w":18,"h":189},
	"rotated": false,
	"trimmed": false,
	"spriteSourceSize": {"x":0,"y":0,"w":18,"h":189},
	"sourceSize": {"w":18,"h":189}
},
{
	"filename": "eyeball-12",
	"frame": {"x":1949,"y":389,"w":18,"h":204},
	"rotated": false,
	"trimmed": false,
	"spriteSourceSize": {"x":0,"y":0,"w":18,"h":204},
	"sourceSize": {"w":18,"h":204}
},
{
	"filename": "eyeball-13",
	"frame": {"x":1969,"y":404,"w":18,"h":219},
	"rotated": false,
	"trimmed": false,
	"spriteSourceSize": {"x":0,"y":0,"w":18,"h":219},
	"sourceSize": {"w":18,"h":219}
},
{
	"filename": "eyeball-14",
	"frame": {"x":1989,"y":410,"w":18,"h":225},
	"rotated": false,
	"trimmed": false,
	"spriteSourceSize": {"x":0,"y":0,"w":18,"h":225},
	"sourceSize": {"w":18,"h":225}
},
{
	"filename": "eyeball-15",
	"frame": {"x":1989,"y":243,"w":18,"h":165},
	"rotated": false,
	"trimmed": false,
	"spriteSourceSize": {"x":0,"y":0,"w":18,"h":165},
	"sourceSize": {"w":18,"h":165}
},
{
	"filename": "eyeball-16",
	"frame": {"x":2023,"y":145,"w":18,"h":105},
	"rotated": false,
	"trimmed": false,
	"spriteSourceSize": {"x":0,"y":0,"w":18,"h":105},
	"sourceSize": {"w":18,"h":105}
},
{
	"filename": "eyeball-17",
	"frame": {"x":211,"y":1,"w":18,"h":45},
	"rotated": false,
	"trimmed": false,
	"spriteSourceSize": {"x":0,"y":0,"w":18,"h":45},
	"sourceSize": {"w":18,"h":45}
},
{
	"filename": "gremlin-0",
	"frame": {"x":203,"y":901,"w":120,"h":192},
	"rotated": false,
	"trimmed": false,
	"spriteSourceSize": {"x":0,"y":0,"w":120,"h":192},
	"sourceSize": {"w":120,"h":192}
},
{
	"filename": "gremlin-1",
	"frame": {"x":325,"y":901,"w":120,"h":192},
	"rotated": false,
	"trimmed": false,
	"spriteSourceSize": {"x":0,"y":0,"w":120,"h":192},
	"sourceSize": {"w":120,"h":192}
},
{
	"filename": "gremlin-2",
	"frame": {"x":447,"y":901,"w":120,"h":192},
	"rotated": false,
	"trimmed": false,
	"spriteSourceSize": {"x":0,"y":0,"w":120,"h":192},
	"sourceSize": {"w":120,"h":192}
},
{
	"filename": "gremlin-3",
	"frame": {"x":569,"y":901,"w":120,"h":192},
	"rotated": false,
	"trimmed": false,
	"spriteSourceSize": {"x":0,"y":0,"w":120,"h":192},
	"sourceSize": {"w":120,"h":192}
},
{
	"filename": "gremlin-4",
	"frame": {"x":691,"y":901,"w":120,"h":192},
	"rotated": false,
	"trimmed": false,
	"spriteSourceSize": {"x":0,"y":0,"w":120,"h":192},
	"sourceSize": {"w":120,"h":192}
},
{
	"filename": "gremlin-5",
	"frame": {"x":813,"y":901,"w":120,"h":192},
	"rotated": false,
	"trimmed": false,
	"spriteSourceSize": {"x":0,"y":0,"w":120,"h":192},
	"sourceSize": {"w":120,"h":192}
},
{
	"filename": "jim_sprite-0",
	"frame": {"x":1575,"y":428,"w":99,"h":162},
	"rotated": false,
	"trimmed": false,
	"spriteSourceSize": {"x":0,"y":0,"w":99,"h":162},
	"sourceSize": {"w":99,"h":162}
},
{
	"filename": "jim_sprite-1",
	"frame": {"x":1806,"y":471,"w":99,"h":162},
	"rotated": false,
	"trimmed": false,
	"spriteSourceSize": {"x":0,"y":0,"w":99,"h":162},
	"sourceSize": {"w":99,"h":162}
},
{
	"filename": "jim_sprite-2",
	"frame": {"x":1445,"y":722,"w":99,"h":162},
	"rotated": false,
	"trimmed": false,
	"spriteSourceSize": {"x":0,"y":0,"w":99,"h":162},
	"sourceSize": {"w":99,"h":162}
},
{
	"filename": "jim_sprite-3",
	"frame": {"x":1546,"y":755,"w":99,"h":162},
	"rotated": false,
	"trimmed": false,
	"spriteSourceSize": {"x":0,"y":0,"w":99,"h":162},
	"sourceSize": {"w":99,"h":162}
},
{
	"filename": "jim_sprite-4",
	"frame": {"x":1647,"y":799,"w":99,"h":162},
	"rotated": false,
	"trimmed": false,
	"spriteSourceSize": {"x":0,"y":0,"w":99,"h":162},
	"sourceSize": {"w":99,"h":162}
},
{
	"filename": "jim_sprite-5",
	"frame": {"x":1748,"y":799,"w":99,"h":162},
	"rotated": false,
	"trimmed": false,
	"spriteSourceSize": {"x":0,"y":0,"w":99,"h":162},
	"sourceSize": {"w":99,"h":162}
},
{
	"filename": "jim_sprite-6",
	"frame": {"x":1849,"y":801,"w":99,"h":162},
	"rotated": false,
	"trimmed": false,
	"spriteSourceSize": {"x":0,"y":0,"w":99,"h":162},
	"sourceSize": {"w":99,"h":162}
},
{
	"filename": "jim_sprite-7",
	"frame": {"x":1445,"y":886,"w":99,"h":162},
	"rotated": false,
	"trimmed": false,
	"spriteSourceSize": {"x":0,"y":0,"w":99,"h":162},
	"sourceSize": {"w":99,"h":162}
},
{
	"filename": "jim_sprite-8",
	"frame": {"x":1,"y":901,"w":99,"h":162},
	"rotated": false,
	"trimmed": false,
	"spriteSourceSize": {"x":0,"y":0,"w":99,"h":162},
	"sourceSize": {"w":99,"h":162}
},
{
	"filename": "jim_sprite-9",
	"frame": {"x":102,"y":901,"w":99,"h":162},
	"rotated": false,
	"trimmed": false,
	"spriteSourceSize": {"x":0,"y":0,"w":99,"h":162},
	"sourceSize": {"w":99,"h":162}
},
{
	"filename": "jim_sprite-10",
	"frame": {"x":1445,"y":558,"w":99,"h":162},
	"rotated": false,
	"trimmed": false,
	"spriteSourceSize": {"x":0,"y":0,"w":99,"h":162},
	"sourceSize": {"w":99,"h":162}
},
{
	"filename": "jim_sprite-11",
	"frame": {"x":1708,"y":635,"w":99,"h":162},
	"rotated": false,
	"trimmed": false,
	"spriteSourceSize": {"x":0,"y":0,"w":99,"h":162},
	"sourceSize": {"w":99,"h":162}
},
{
	"filename": "jim_sprite-12",
	"frame": {"x":1809,"y":635,"w":99,"h":162},
	"rotated": false,
	"trimmed": false,
	"spriteSourceSize": {"x":0,"y":0,"w":99,"h":162},
	"sourceSize": {"w":99,"h":162}
},
{
	"filename": "jim_sprite-13",
	"frame": {"x":1910,"y":637,"w":99,"h":162},
	"rotated": false,
	"trimmed": false,
	"spriteSourceSize": {"x":0,"y":0,"w":99,"h":162},
	"sourceSize": {"w":99,"h":162}
},
{
	"filename": "pacMan-0",
	"frame": {"x":1845,"y":1,"w":60,"h":60},
	"rotated": false,
	"trimmed": false,
	"spriteSourceSize": {"x":0,"y":0,"w":60,"h":60},
	"sourceSize": {"w":60,"h":60}
},
{
	"filename": "pacMan-1",
	"frame": {"x":1907,"y":1,"w":60,"h":60},
	"rotated": false,
	"trimmed": false,
	"spriteSourceSize": {"x":0,"y":0,"w":60,"h":60},
	"sourceSize": {"w":60,"h":60}
},
{
	"filename": "pacMan-2",
	"frame": {"x":1969,"y":1,"w":60,"h":60},
	"rotated": false,
	"trimmed": false,
	"spriteSourceSize": {"x":0,"y":0,"w":60,"h":60},
	"sourceSize": {"w":60,"h":60}
},
{
	"filename": "phonebooth-0",
	"frame": {"x":935,"y":901,"w":117,"h":255},
	"rotated": false,
	"trimmed": false,
	"spriteSourceSize": {"x":0,"y":0,"w":117,"h":255},
	"sourceSize": {"w":117,"h":255}
},
{
	"filename": "phonebooth-1",
	"frame": {"x":1054,"y":901,"w":117,"h":255},
	"rotated": false,
	"trimmed": false,
	"spriteSourceSize": {"x":0,"y":0,"w":117,"h":255},
	"sourceSize": {"w":117,"h":255}
},
{
	"filename": "phonebooth-2",
	"frame": {"x":1903,"y":965,"w":117,"h":255},
	"rotated": false,
	"trimmed": false,
	"spriteSourceSize": {"x":0,"y":0,"w":117,"h":255},
	"sourceSize": {"w":117,"h":255}
},
{
	"filename": "phonebooth-3",
	"frame": {"x":1411,"y":1050,"w":117,"h":255},
	"rotated": false,
	"trimmed": false,
	"spriteSourceSize": {"x":0,"y":0,"w":117,"h":255},
	"sourceSize": {"w":117,"h":255}
},
{
	"filename": "phonebooth-4",
	"frame": {"x":1,"y":1065,"w":117,"h":255},
	"rotated": false,
	"trimmed": false,
	"spriteSourceSize": {"x":0,"y":0,"w":117,"h":255},
	"sourceSize": {"w":117,"h":255}
},
{
	"filename": "phonebooth-5",
	"frame": {"x":120,"y":1095,"w":117,"h":255},
	"rotated": false,
	"trimmed": false,
	"spriteSourceSize": {"x":0,"y":0,"w":117,"h":255},
	"sourceSize": {"w":117,"h":255}
},
{
	"filename": "phonebooth-6",
	"frame": {"x":239,"y":1095,"w":117,"h":255},
	"rotated": false,
	"trimmed": false,
	"spriteSourceSize": {"x":0,"y":0,"w":117,"h":255},
	"sourceSize": {"w":117,"h":255}
},
{
	"filename": "phonebooth-7",
	"frame": {"x":358,"y":1095,"w":117,"h":255},
	"rotated": false,
	"trimmed": false,
	"spriteSourceSize": {"x":0,"y":0,"w":117,"h":255},
	"sourceSize": {"w":117,"h":255}
},
{
	"filename": "phonebooth-8",
	"frame": {"x":477,"y":1095,"w":117,"h":255},
	"rotated": false,
	"trimmed": false,
	"spriteSourceSize": {"x":0,"y":0,"w":117,"h":255},
	"sourceSize": {"w":117,"h":255}
},
{
	"filename": "phonebooth-9",
	"frame": {"x":596,"y":1095,"w":117,"h":255},
	"rotated": false,
	"trimmed": false,
	"spriteSourceSize": {"x":0,"y":0,"w":117,"h":255},
	"sourceSize": {"w":117,"h":255}
},
{
	"filename": "phonebooth-10",
	"frame": {"x":1173,"y":901,"w":117,"h":255},
	"rotated": false,
	"trimmed": false,
	"spriteSourceSize": {"x":0,"y":0,"w":117,"h":255},
	"sourceSize": {"w":117,"h":255}
},
{
	"filename": "phonebooth-11",
	"frame": {"x":1292,"y":901,"w":117,"h":255},
	"rotated": false,
	"trimmed": false,
	"spriteSourceSize": {"x":0,"y":0,"w":117,"h":255},
	"sourceSize": {"w":117,"h":255}
},
{
	"filename": "phonebooth-12",
	"frame": {"x":1546,"y":963,"w":117,"h":255},
	"rotated": false,
	"trimmed": false,
	"spriteSourceSize": {"x":0,"y":0,"w":117,"h":255},
	"sourceSize": {"w":117,"h":255}
},
{
	"filename": "phonebooth-13",
	"frame": {"x":1665,"y":963,"w":117,"h":255},
	"rotated": false,
	"trimmed": false,
	"spriteSourceSize": {"x":0,"y":0,"w":117,"h":255},
	"sourceSize": {"w":117,"h":255}
},
{
	"filename": "phonebooth-14",
	"frame": {"x":1784,"y":965,"w":117,"h":255},
	"rotated": false,
	"trimmed": false,
	"spriteSourceSize": {"x":0,"y":0,"w":117,"h":255},
	"sourceSize": {"w":117,"h":255}
},
{
	"filename": "protonbeam-0",
	"frame": {"x":231,"y":1,"w":720,"h":48},
	"rotated": false,
	"trimmed": false,
	"spriteSourceSize": {"x":0,"y":0,"w":720,"h":48},
	"sourceSize": {"w":720,"h":48}
},
{
	"filename": "protonbeam-1",
	"frame": {"x":953,"y":1,"w":720,"h":48},
	"rotated": false,
	"trimmed": false,
	"spriteSourceSize": {"x":0,"y":0,"w":720,"h":48},
	"sourceSize": {"w":720,"h":48}
},
{
	"filename": "protonbeam-2",
	"frame": {"x":1,"y":301,"w":720,"h":48},
	"rotated": false,
	"trimmed": false,
	"spriteSourceSize": {"x":0,"y":0,"w":720,"h":48},
	"sourceSize": {"w":720,"h":48}
},
{
	"filename": "protonbeam-3",
	"frame": {"x":723,"y":551,"w":720,"h":48},
	"rotated": false,
	"trimmed": false,
	"spriteSourceSize": {"x":0,"y":0,"w":720,"h":48},
	"sourceSize": {"w":720,"h":48}
},
{
	"filename": "protonbeam-4",
	"frame": {"x":1,"y":751,"w":720,"h":48},
	"rotated": false,
	"trimmed": false,
	"spriteSourceSize": {"x":0,"y":0,"w":720,"h":48},
	"sourceSize": {"w":720,"h":48}
},
{
	"filename": "protonbeam-5",
	"frame": {"x":723,"y":751,"w":720,"h":48},
	"rotated": false,
	"trimmed": false,
	"spriteSourceSize": {"x":0,"y":0,"w":720,"h":48},
	"sourceSize": {"w":720,"h":48}
},
{
	"filename": "protonbeam-6",
	"frame": {"x":1,"y":801,"w":720,"h":48},
	"rotated": false,
	"trimmed": false,
	"spriteSourceSize": {"x":0,"y":0,"w":720,"h":48},
	"sourceSize": {"w":720,"h":48}
},
{
	"filename": "protonbeam-7",
	"frame": {"x":723,"y":801,"w":720,"h":48},
	"rotated": false,
	"trimmed": false,
	"spriteSourceSize": {"x":0,"y":0,"w":720,"h":48},
	"sourceSize": {"w":720,"h":48}
},
{
	"filename": "protonbeam-8",
	"frame": {"x":1,"y":851,"w":720,"h":48},
	"rotated": false,
	"trimmed": false,
	"spriteSourceSize": {"x":0,"y":0,"w":720,"h":48},
	"sourceSize": {"w":720,"h":48}
},
{
	"filename": "protonbeam-9",
	"frame": {"x":723,"y":851,"w":720,"h":48},
	"rotated": false,
	"trimmed": false,
	"spriteSourceSize": {"x":0,"y":0,"w":720,"h":48},
	"sourceSize": {"w":720,"h":48}
},
{
	"filename": "protonbeam-10",
	"frame": {"x":119,"y":51,"w":720,"h":48},
	"rotated": false,
	"trimmed": false,
	"spriteSourceSize": {"x":0,"y":0,"w":720,"h":48},
	"sourceSize": {"w":720,"h":48}
},
{
	"filename": "protonbeam-11",
	"frame": {"x":841,"y":51,"w":720,"h":48},
	"rotated": false,
	"trimmed": false,
	"spriteSourceSize": {"x":0,"y":0,"w":720,"h":48},
	"sourceSize": {"w":720,"h":48}
},
{
	"filename": "protonbeam-12",
	"frame": {"x":1,"y":101,"w":720,"h":48},
	"rotated": false,
	"trimmed": false,
	"spriteSourceSize": {"x":0,"y":0,"w":720,"h":48},
	"sourceSize": {"w":720,"h":48}
},
{
	"filename": "protonbeam-13",
	"frame": {"x":723,"y":101,"w":720,"h":48},
	"rotated": false,
	"trimmed": false,
	"spriteSourceSize": {"x":0,"y":0,"w":720,"h":48},
	"sourceSize": {"w":720,"h":48}
},
{
	"filename": "protonbeam-14",
	"frame": {"x":1,"y":151,"w":720,"h":48},
	"rotated": false,
	"trimmed": false,
	"spriteSourceSize": {"x":0,"y":0,"w":720,"h":48},
	"sourceSize": {"w":720,"h":48}
},
{
	"filename": "protonbeam-15",
	"frame": {"x":723,"y":151,"w":720,"h":48},
	"rotated": false,
	"trimmed": false,
	"spriteSourceSize": {"x":0,"y":0,"w":720,"h":48},
	"sourceSize": {"w":720,"h":48}
},
{
	"filename": "protonbeam-16",
	"frame": {"x":1,"y":201,"w":720,"h":48},
	"rotated": false,
	"trimmed": false,
	"spriteSourceSize": {"x":0,"y":0,"w":720,"h":48},
	"sourceSize": {"w":720,"h":48}
},
{
	"filename": "protonbeam-17",
	"frame": {"x":723,"y":201,"w":720,"h":48},
	"rotated": false,
	"trimmed": false,
	"spriteSourceSize": {"x":0,"y":0,"w":720,"h":48},
	"sourceSize": {"w":720,"h":48}
},
{
	"filename": "protonbeam-18",
	"frame": {"x":1,"y":251,"w":720,"h":48},
	"rotated": false,
	"trimmed": false,
	"spriteSourceSize": {"x":0,"y":0,"w":720,"h":48},
	"sourceSize": {"w":720,"h":48}
},
{
	"filename": "protonbeam-19",
	"frame": {"x":723,"y":251,"w":720,"h":48},
	"rotated": false,
	"trimmed": false,
	"spriteSourceSize": {"x":0,"y":0,"w":720,"h":48},
	"sourceSize": {"w":720,"h":48}
},
{
	"filename": "protonbeam-20",
	"frame": {"x":723,"y":301,"w":720,"h":48},
	"rotated": false,
	"trimmed": false,
	"spriteSourceSize": {"x":0,"y":0,"w":720,"h":48},
	"sourceSize": {"w":720,"h":48}
},
{
	"filename": "protonbeam-21",
	"frame": {"x":1,"y":351,"w":720,"h":48},
	"rotated": false,
	"trimmed": false,
	"spriteSourceSize": {"x":0,"y":0,"w":720,"h":48},
	"sourceSize": {"w":720,"h":48}
},
{
	"filename": "protonbeam-22",
	"frame": {"x":723,"y":351,"w":720,"h":48},
	"rotated": false,
	"trimmed": false,
	"spriteSourceSize": {"x":0,"y":0,"w":720,"h":48},
	"sourceSize": {"w":720,"h":48}
},
{
	"filename": "protonbeam-23",
	"frame": {"x":1,"y":401,"w":720,"h":48},
	"rotated": false,
	"trimmed": false,
	"spriteSourceSize": {"x":0,"y":0,"w":720,"h":48},
	"sourceSize": {"w":720,"h":48}
},
{
	"filename": "protonbeam-24",
	"frame": {"x":723,"y":401,"w":720,"h":48},
	"rotated": false,
	"trimmed": false,
	"spriteSourceSize": {"x":0,"y":0,"w":720,"h":48},
	"sourceSize": {"w":720,"h":48}
},
{
	"filename": "protonbeam-25",
	"frame": {"x":1,"y":451,"w":720,"h":48},
	"rotated": false,
	"trimmed": false,
	"spriteSourceSize": {"x":0,"y":0,"w":720,"h":48},
	"sourceSize": {"w":720,"h":48}
},
{
	"filename": "protonbeam-26",
	"frame": {"x":723,"y":451,"w":720,"h":48},
	"rotated": false,
	"trimmed": false,
	"spriteSourceSize": {"x":0,"y":0,"w":720,"h":48},
	"sourceSize": {"w":720,"h":48}
},
{
	"filename": "protonbeam-27",
	"frame": {"x":1,"y":501,"w":720,"h":48},
	"rotated": false,
	"trimmed": false,
	"spriteSourceSize": {"x":0,"y":0,"w":720,"h":48},
	"sourceSize": {"w":720,"h":48}
},
{
	"filename": "protonbeam-28",
	"frame": {"x":723,"y":501,"w":720,"h":48},
	"rotated": false,
	"trimmed": false,
	"spriteSourceSize": {"x":0,"y":0,"w":720,"h":48},
	"sourceSize": {"w":720,"h":48}
},
{
	"filename": "protonbeam-29",
	"frame": {"x":1,"y":551,"w":720,"h":48},
	"rotated": false,
	"trimmed": false,
	"spriteSourceSize": {"x":0,"y":0,"w":720,"h":48},
	"sourceSize": {"w":720,"h":48}
},
{
	"filename": "protonbeam-30",
	"frame": {"x":1,"y":601,"w":720,"h":48},
	"rotated": false,
	"trimmed": false,
	"spriteSourceSize": {"x":0,"y":0,"w":720,"h":48},
	"sourceSize": {"w":720,"h":48}
},
{
	"filename": "protonbeam-31",
	"frame": {"x":723,"y":601,"w":720,"h":48},
	"rotated": false,
	"trimmed": false,
	"spriteSourceSize": {"x":0,"y":0,"w":720,"h":48},
	"sourceSize": {"w":720,"h":48}
},
{
	"filename": "protonbeam-32",
	"frame": {"x":1,"y":651,"w":720,"h":48},
	"rotated": false,
	"trimmed": false,
	"spriteSourceSize": {"x":0,"y":0,"w":720,"h":48},
	"sourceSize": {"w":720,"h":48}
},
{
	"filename": "protonbeam-33",
	"frame": {"x":723,"y":651,"w":720,"h":48},
	"rotated": false,
	"trimmed": false,
	"spriteSourceSize": {"x":0,"y":0,"w":720,"h":48},
	"sourceSize": {"w":720,"h":48}
},
{
	"filename": "protonbeam-34",
	"frame": {"x":1,"y":701,"w":720,"h":48},
	"rotated": false,
	"trimmed": false,
	"spriteSourceSize": {"x":0,"y":0,"w":720,"h":48},
	"sourceSize": {"w":720,"h":48}
},
{
	"filename": "protonbeam-35",
	"frame": {"x":723,"y":701,"w":720,"h":48},
	"rotated": false,
	"trimmed": false,
	"spriteSourceSize": {"x":0,"y":0,"w":720,"h":48},
	"sourceSize": {"w":720,"h":48}
},
{
	"filename": "shadedDark01",
	"frame": {"x":1445,"y":175,"w":96,"h":100},
	"rotated": false,
	"trimmed": false,
	"spriteSourceSize": {"x":0,"y":0,"w":96,"h":100},
	"sourceSize": {"w":96,"h":100}
},
{
	"filename": "shadedDark07",
	"frame": {"x":1546,"y":593,"w":160,"h":160},
	"rotated": false,
	"trimmed": false,
	"spriteSourceSize": {"x":0,"y":0,"w":160,"h":160},
	"sourceSize": {"w":160,"h":160}
},
{
	"filename": "shadedDark13",
	"frame": {"x":1675,"y":1,"w":48,"h":48},
	"rotated": false,
	"trimmed": false,
	"spriteSourceSize": {"x":0,"y":0,"w":48,"h":48},
	"sourceSize": {"w":48,"h":48}
},
{
	"filename": "shadedDark15",
	"frame": {"x":1725,"y":1,"w":48,"h":48},
	"rotated": false,
	"trimmed": false,
	"spriteSourceSize": {"x":0,"y":0,"w":48,"h":48},
	"sourceSize": {"w":48,"h":48}
},
{
	"filename": "shadedDark30",
	"frame": {"x":1775,"y":1,"w":48,"h":48},
	"rotated": false,
	"trimmed": false,
	"spriteSourceSize": {"x":0,"y":0,"w":48,"h":48},
	"sourceSize": {"w":48,"h":48}
},
{
	"filename": "shadedDark36",
	"frame": {"x":1955,"y":63,"w":80,"h":80},
	"rotated": false,
	"trimmed": false,
	"spriteSourceSize": {"x":0,"y":0,"w":80,"h":80},
	"sourceSize": {"w":80,"h":80}
},
{
	"filename": "simon-0",
	"frame": {"x":1759,"y":137,"w":120,"h":96},
	"rotated": false,
	"trimmed": false,
	"spriteSourceSize": {"x":0,"y":0,"w":120,"h":96},
	"sourceSize": {"w":120,"h":96}
},
{
	"filename": "simon-1",
	"frame": {"x":1901,"y":145,"w":120,"h":96},
	"rotated": false,
	"trimmed": false,
	"spriteSourceSize": {"x":0,"y":0,"w":120,"h":96},
	"sourceSize": {"w":120,"h":96}
},
{
	"filename": "simon-2",
	"frame": {"x":1543,"y":199,"w":120,"h":96},
	"rotated": false,
	"trimmed": false,
	"spriteSourceSize": {"x":0,"y":0,"w":120,"h":96},
	"sourceSize": {"w":120,"h":96}
},
{
	"filename": "simon-3",
	"frame": {"x":1705,"y":235,"w":120,"h":96},
	"rotated": false,
	"trimmed": false,
	"spriteSourceSize": {"x":0,"y":0,"w":120,"h":96},
	"sourceSize": {"w":120,"h":96}
},
{
	"filename": "simon-4",
	"frame": {"x":1827,"y":243,"w":120,"h":96},
	"rotated": false,
	"trimmed": false,
	"spriteSourceSize": {"x":0,"y":0,"w":120,"h":96},
	"sourceSize": {"w":120,"h":96}
},
{
	"filename": "simon-5",
	"frame": {"x":1445,"y":297,"w":120,"h":96},
	"rotated": false,
	"trimmed": false,
	"spriteSourceSize": {"x":0,"y":0,"w":120,"h":96},
	"sourceSize": {"w":120,"h":96}
},
{
	"filename": "simon-6",
	"frame": {"x":1567,"y":330,"w":120,"h":96},
	"rotated": false,
	"trimmed": false,
	"spriteSourceSize": {"x":0,"y":0,"w":120,"h":96},
	"sourceSize": {"w":120,"h":96}
},
{
	"filename": "skeletor-0",
	"frame": {"x":715,"y":1095,"w":170,"h":280},
	"rotated": false,
	"trimmed": false,
	"spriteSourceSize": {"x":0,"y":0,"w":170,"h":280},
	"sourceSize": {"w":170,"h":280}
},
{
	"filename": "skeletor-1",
	"frame": {"x":887,"y":1158,"w":170,"h":280},
	"rotated": false,
	"trimmed": false,
	"spriteSourceSize": {"x":0,"y":0,"w":170,"h":280},
	"sourceSize": {"w":170,"h":280}
},
{
	"filename": "skeletor-2",
	"frame": {"x":1059,"y":1158,"w":170,"h":280},
	"rotated": false,
	"trimmed": false,
	"spriteSourceSize": {"x":0,"y":0,"w":170,"h":280},
	"sourceSize": {"w":170,"h":280}
},
{
	"filename": "slimer-0",
	"frame": {"x":1689,"y":333,"w":128,"h":128},
	"rotated": false,
	"trimmed": false,
	"spriteSourceSize": {"x":0,"y":0,"w":128,"h":128},
	"sourceSize": {"w":128,"h":128}
},
{
	"filename": "slimer-1",
	"frame": {"x":1819,"y":341,"w":128,"h":128},
	"rotated": false,
	"trimmed": false,
	"spriteSourceSize": {"x":0,"y":0,"w":128,"h":128},
	"sourceSize": {"w":128,"h":128}
},
{
	"filename": "slimer-2",
	"frame": {"x":1445,"y":428,"w":128,"h":128},
	"rotated": false,
	"trimmed": false,
	"spriteSourceSize": {"x":0,"y":0,"w":128,"h":128},
	"sourceSize": {"w":128,"h":128}
},
{
	"filename": "slimer-3",
	"frame": {"x":1676,"y":463,"w":128,"h":128},
	"rotated": false,
	"trimmed": false,
	"spriteSourceSize": {"x":0,"y":0,"w":128,"h":128},
	"sourceSize": {"w":128,"h":128}
}],
"meta": {
	"app": "https://www.codeandweb.com/texturepacker",
	"version": "1.0",
	"image": "texture.png",
	"format": "RGBA8888",
	"size": {"w":2048,"h":2048},
	"scale": "1",
	"smartupdate": "$TexturePacker:SmartUpdate:6463a2f2d255c96ae9d78d79d0e575f7:5649dbf2c24e502930d58894c6d7524c:88db1022cd6b660616541d2788fcd4f7$"
}
}
